[
  {
    "url": "https://www.primevideo.com/-/de/livetv",
    "final_url": "https://www.primevideo.com/-/de/livetv",
    "ok": true,
    "error": "",
    "bytes": 1759185,
    "json_blocks": 92,
    "html_keyword_hits": [
      {
        "keyword": "prime",
        "count": 110
      },
      {
        "keyword": "prime video",
        "count": 16
      },
      {
        "keyword": "sport",
        "count": 109
      },
      {
        "keyword": "sports",
        "count": 54
      },
      {
        "keyword": "livetv",
        "count": 208
      },
      {
        "keyword": "linear",
        "count": 2534
      },
      {
        "keyword": "channel",
        "count": 273
      },
      {
        "keyword": "station",
        "count": 506
      },
      {
        "keyword": "schedule",
        "count": 64
      },
      {
        "keyword": "atp",
        "count": 2
      },
      {
        "keyword": "fußball",
        "count": 10
      },
      {
        "keyword": "football",
        "count": 16
      },
      {
        "keyword": "world cup",
        "count": 12
      },
      {
        "keyword": "wm",
        "count": 389
      },
      {
        "keyword": "soccer",
        "count": 3
      }
    ]
  },
  {
    "url": "https://www.primevideo.com/-/en/livetv",
    "final_url": "https://www.primevideo.com/-/en/livetv",
    "ok": true,
    "error": "",
    "bytes": 1760734,
    "json_blocks": 92,
    "html_keyword_hits": [
      {
        "keyword": "prime",
        "count": 110
      },
      {
        "keyword": "prime video",
        "count": 16
      },
      {
        "keyword": "sport",
        "count": 87
      },
      {
        "keyword": "sports",
        "count": 72
      },
      {
        "keyword": "live tv",
        "count": 11
      },
      {
        "keyword": "livetv",
        "count": 208
      },
      {
        "keyword": "linear",
        "count": 2534
      },
      {
        "keyword": "channel",
        "count": 273
      },
      {
        "keyword": "station",
        "count": 508
      },
      {
        "keyword": "schedule",
        "count": 65
      },
      {
        "keyword": "atp",
        "count": 5
      },
      {
        "keyword": "football",
        "count": 16
      },
      {
        "keyword": "world cup",
        "count": 22
      },
      {
        "keyword": "wm",
        "count": 270
      },
      {
        "keyword": "soccer",
        "count": 9
      }
    ]
  },
  {
    "url": "https://www.primevideo.com/-/de/sports?ref_=atv_hm_sports_c_9zZ8D2_hom",
    "final_url": "https://www.primevideo.com/-/de/sports?ref_=atv_hm_sports_c_9zZ8D2_hom",
    "ok": true,
    "error": "",
    "bytes": 1763262,
    "json_blocks": 138,
    "html_keyword_hits": [
      {
        "keyword": "prime",
        "count": 440
      },
      {
        "keyword": "prime video",
        "count": 16
      },
      {
        "keyword": "sport",
        "count": 769
      },
      {
        "keyword": "sports",
        "count": 412
      },
      {
        "keyword": "livetv",
        "count": 4
      },
      {
        "keyword": "linear",
        "count": 1365
      },
      {
        "keyword": "channel",
        "count": 1636
      },
      {
        "keyword": "station",
        "count": 211
      },
      {
        "keyword": "schedule",
        "count": 21
      },
      {
        "keyword": "tennis",
        "count": 29
      },
      {
        "keyword": "atp",
        "count": 37
      },
      {
        "keyword": "wta",
        "count": 14
      },
      {
        "keyword": "fußball",
        "count": 10
      },
      {
        "keyword": "football",
        "count": 60
      },
      {
        "keyword": "world cup",
        "count": 105
      },
      {
        "keyword": "wm",
        "count": 415
      },
      {
        "keyword": "soccer",
        "count": 19
      }
    ]
  },
  {
    "url": "https://www.primevideo.com/-/en/sports?ref_=atv_hm_sports_c_9zZ8D2_hom",
    "final_url": "https://www.primevideo.com/-/en/sports?ref_=atv_hm_sports_c_9zZ8D2_hom",
    "ok": true,
    "error": "",
    "bytes": 1775100,
    "json_blocks": 138,
    "html_keyword_hits": [
      {
        "keyword": "prime",
        "count": 443
      },
      {
        "keyword": "prime video",
        "count": 16
      },
      {
        "keyword": "sport",
        "count": 497
      },
      {
        "keyword": "sports",
        "count": 461
      },
      {
        "keyword": "live tv",
        "count": 7
      },
      {
        "keyword": "livetv",
        "count": 4
      },
      {
        "keyword": "linear",
        "count": 1365
      },
      {
        "keyword": "channel",
        "count": 1640
      },
      {
        "keyword": "station",
        "count": 216
      },
      {
        "keyword": "schedule",
        "count": 22
      },
      {
        "keyword": "tennis",
        "count": 29
      },
      {
        "keyword": "atp",
        "count": 34
      },
      {
        "keyword": "wta",
        "count": 4
      },
      {
        "keyword": "football",
        "count": 102
      },
      {
        "keyword": "world cup",
        "count": 118
      },
      {
        "keyword": "wm",
        "count": 454
      },
      {
        "keyword": "soccer",
        "count": 30
      }
    ]
  },
  {
    "url": "https://www.amazon.de/-/de/gp/video/livetv",
    "final_url": "https://www.amazon.de/-/de/gp/video/livetv",
    "ok": true,
    "error": "",
    "bytes": 2134782,
    "json_blocks": 135,
    "html_keyword_hits": [
      {
        "keyword": "prime",
        "count": 181
      },
      {
        "keyword": "amazon prime",
        "count": 1
      },
      {
        "keyword": "prime video",
        "count": 17
      },
      {
        "keyword": "sport",
        "count": 151
      },
      {
        "keyword": "sports",
        "count": 74
      },
      {
        "keyword": "livetv",
        "count": 53
      },
      {
        "keyword": "linear",
        "count": 4284
      },
      {
        "keyword": "channel",
        "count": 184
      },
      {
        "keyword": "station",
        "count": 830
      },
      {
        "keyword": "schedule",
        "count": 65
      },
      {
        "keyword": "atp",
        "count": 5
      },
      {
        "keyword": "wta",
        "count": 6
      },
      {
        "keyword": "fußball",
        "count": 13
      },
      {
        "keyword": "football",
        "count": 21
      },
      {
        "keyword": "world cup",
        "count": 16
      },
      {
        "keyword": "wm",
        "count": 332
      },
      {
        "keyword": "soccer",
        "count": 4
      }
    ]
  },
  {
    "url": "https://www.amazon.de/-/en/gp/video/livetv",
    "final_url": "https://www.amazon.de/-/en/gp/video/livetv",
    "ok": true,
    "error": "",
    "bytes": 2151707,
    "json_blocks": 135,
    "html_keyword_hits": [
      {
        "keyword": "prime",
        "count": 181
      },
      {
        "keyword": "amazon prime",
        "count": 1
      },
      {
        "keyword": "prime video",
        "count": 17
      },
      {
        "keyword": "sport",
        "count": 117
      },
      {
        "keyword": "sports",
        "count": 99
      },
      {
        "keyword": "live tv",
        "count": 4
      },
      {
        "keyword": "livetv",
        "count": 53
      },
      {
        "keyword": "linear",
        "count": 4284
      },
      {
        "keyword": "channel",
        "count": 184
      },
      {
        "keyword": "station",
        "count": 832
      },
      {
        "keyword": "schedule",
        "count": 67
      },
      {
        "keyword": "atp",
        "count": 8
      },
      {
        "keyword": "football",
        "count": 21
      },
      {
        "keyword": "world cup",
        "count": 31
      },
      {
        "keyword": "wm",
        "count": 336
      },
      {
        "keyword": "soccer",
        "count": 14
      }
    ]
  },
  {
    "url": "https://www.amazon.de/-/de/gp/video/sports",
    "final_url": "https://www.amazon.de/-/de/gp/video/sports",
    "ok": true,
    "error": "",
    "bytes": 958372,
    "json_blocks": 80,
    "html_keyword_hits": [
      {
        "keyword": "prime",
        "count": 325
      },
      {
        "keyword": "amazon prime",
        "count": 1
      },
      {
        "keyword": "prime video",
        "count": 24
      },
      {
        "keyword": "sport",
        "count": 299
      },
      {
        "keyword": "sports",
        "count": 183
      },
      {
        "keyword": "linear",
        "count": 15
      },
      {
        "keyword": "channel",
        "count": 295
      },
      {
        "keyword": "station",
        "count": 5
      },
      {
        "keyword": "schedule",
        "count": 2
      },
      {
        "keyword": "wta",
        "count": 4
      },
      {
        "keyword": "fußball",
        "count": 13
      },
      {
        "keyword": "fussball",
        "count": 4
      },
      {
        "keyword": "world cup",
        "count": 10
      },
      {
        "keyword": "wm",
        "count": 234
      },
      {
        "keyword": "soccer",
        "count": 2
      }
    ]
  },
  {
    "url": "https://www.amazon.de/-/en/gp/video/sports",
    "final_url": "https://www.amazon.de/-/en/gp/video/sports",
    "ok": true,
    "error": "",
    "bytes": 954207,
    "json_blocks": 80,
    "html_keyword_hits": [
      {
        "keyword": "prime",
        "count": 337
      },
      {
        "keyword": "amazon prime",
        "count": 1
      },
      {
        "keyword": "prime video",
        "count": 24
      },
      {
        "keyword": "sport",
        "count": 297
      },
      {
        "keyword": "sports",
        "count": 270
      },
      {
        "keyword": "linear",
        "count": 15
      },
      {
        "keyword": "channel",
        "count": 307
      },
      {
        "keyword": "station",
        "count": 7
      },
      {
        "keyword": "schedule",
        "count": 4
      },
      {
        "keyword": "wta",
        "count": 6
      },
      {
        "keyword": "football",
        "count": 9
      },
      {
        "keyword": "world cup",
        "count": 15
      },
      {
        "keyword": "wm",
        "count": 236
      },
      {
        "keyword": "soccer",
        "count": 5
      }
    ]
  }
]