{
  "ok": true,
  "generated_at_utc": "2026-07-15T01:49:02.102492+00:00",
  "urls": [
    "https://www.primevideo.com/-/de/livetv",
    "https://www.primevideo.com/-/en/livetv",
    "https://www.primevideo.com/-/de/sports?ref_=atv_hm_sports_c_9zZ8D2_hom",
    "https://www.primevideo.com/-/en/sports?ref_=atv_hm_sports_c_9zZ8D2_hom",
    "https://www.amazon.de/-/de/gp/video/livetv",
    "https://www.amazon.de/-/en/gp/video/livetv",
    "https://www.amazon.de/-/de/gp/video/sports",
    "https://www.amazon.de/-/en/gp/video/sports"
  ],
  "pages_total": 8,
  "pages_ok": 8,
  "discovered_links": 1044,
  "fetched_links": 100,
  "fetched_links_ok": 100,
  "stations": 89751,
  "schedule_events": 12457,
  "prime_candidates": 97647,
  "prime_sport_candidates": 37337,
  "hints": 128243,
  "top_station_titles": [
    [
      "Live ansehen",
      2762
    ],
    [
      "Paid Programming",
      1815
    ],
    [
      "Season 3",
      1521
    ],
    [
      "The Hunt For the Chameleon Killer",
      1353
    ],
    [
      "The Sit",
      1098
    ],
    [
      "TMZ",
      1057
    ],
    [
      "FOX 4 All Day",
      976
    ],
    [
      "Season 5",
      936
    ],
    [
      "LiveNOW from FOX",
      735
    ],
    [
      "TMZ Live",
      610
    ],
    [
      "Headlines from CNN",
      492
    ],
    [
      "Pokerstars Big Game on Tour",
      488
    ],
    [
      "Season 6",
      468
    ],
    [
      "LiveNOW by FOX",
      449
    ],
    [
      "FOX News Radio",
      408
    ],
    [
      "CNN Newsroom Live",
      369
    ],
    [
      "FOX News Talk",
      367
    ],
    [
      "Total Sports 360",
      366
    ],
    [
      "Harry Potter Night",
      366
    ],
    [
      "Local News From the Bay Area",
      366
    ],
    [
      "ABCNL Prime With Linsey Davis",
      328
    ],
    [
      "ABC World News Now",
      328
    ],
    [
      "Good Morning America First Look",
      328
    ],
    [
      "Green Zone",
      328
    ],
    [
      "Final Destination",
      328
    ],
    [
      "Final Destination 2",
      328
    ],
    [
      "Final Destination 3",
      328
    ],
    [
      "FOX Weather First",
      326
    ],
    [
      "American League All-Stars at National League All-Stars",
      325
    ],
    [
      "Halbfinale: Frankreich - Spanien",
      312
    ],
    [
      "America First",
      287
    ],
    [
      "LiveNOW From FOX",
      284
    ],
    [
      "Amanpour and Company",
      246
    ],
    [
      "A Power Play",
      246
    ],
    [
      "From Snoop to Nuts",
      246
    ],
    [
      "Desperado",
      246
    ],
    [
      "CNN NewsNight With Abby Phillip",
      246
    ],
    [
      "The Houdini",
      246
    ],
    [
      "FIFA World Cup on FOX After Hours With James Corden",
      244
    ],
    [
      "Family Feud",
      244
    ],
    [
      "The Aging Brain",
      244
    ],
    [
      "Hannity",
      244
    ],
    [
      "Gutfeld!",
      244
    ],
    [
      "Fox News at Night",
      244
    ],
    [
      "Flawless 1776 Silver",
      244
    ],
    [
      "Punto final",
      244
    ],
    [
      "The Believer's Walk of Faith",
      244
    ],
    [
      "NFL Night",
      244
    ],
    [
      "2000s Night",
      244
    ],
    [
      "A Celebration of Elton John",
      244
    ],
    [
      "Good Nite LA",
      244
    ],
    [
      "West Coast News Wrap",
      244
    ],
    [
      "FOX 2 San Francisco",
      244
    ],
    [
      "FOX 35 News",
      244
    ],
    [
      "Season 2026",
      241
    ],
    [
      "Sendepause",
      234
    ],
    [
      "CNN Headline Express",
      205
    ],
    [
      "The Director",
      205
    ],
    [
      "AMC",
      205
    ],
    [
      "IFC",
      205
    ],
    [
      "The Walking Dead Channel",
      205
    ],
    [
      "Sundance TV",
      205
    ],
    [
      "BBC America",
      205
    ],
    [
      "AMC +",
      205
    ],
    [
      "Cinemax Action",
      205
    ],
    [
      "Cinemax HD East",
      205
    ],
    [
      "Final Destination 5",
      205
    ],
    [
      "Cinemax Classics",
      205
    ],
    [
      "Cinemax West",
      205
    ],
    [
      "Cinemax Hits",
      205
    ],
    [
      "MAX Latino East",
      205
    ],
    [
      "CNN Originals",
      205
    ],
    [
      "CNN Stream",
      205
    ],
    [
      "CNN International",
      205
    ],
    [
      "MGM+ MARQUEE",
      205
    ],
    [
      "MGM+ DRIVE-IN",
      205
    ],
    [
      "MGM+",
      205
    ],
    [
      "MGM+ HITS",
      205
    ],
    [
      "Fox Justice",
      205
    ],
    [
      "Fox Weather",
      205
    ],
    [
      "Fox Weather @ Night",
      204
    ],
    [
      "FOX 5 Washington, DC",
      203
    ],
    [
      "Fox 5 Plus",
      203
    ],
    [
      "FOX News Channel",
      203
    ],
    [
      "FS1",
      203
    ],
    [
      "FS2",
      203
    ],
    [
      "FOX Business",
      203
    ],
    [
      "FOX Weather",
      203
    ],
    [
      "Big Ten Network",
      203
    ],
    [
      "FOX Deportes",
      203
    ],
    [
      "FOX Soul",
      203
    ],
    [
      "The TMZ Channel",
      203
    ],
    [
      "The Masked Singer",
      203
    ],
    [
      "FOX Local Los Angeles",
      203
    ],
    [
      "FOX Local Detroit",
      203
    ],
    [
      "FOX Local Dallas Fort Worth",
      203
    ],
    [
      "FOX Local Atlanta",
      203
    ],
    [
      "FOX Local San Francisco",
      203
    ],
    [
      "FOX Local Orlando",
      203
    ],
    [
      "Best Exotic Marigold Hotel",
      195
    ]
  ],
  "top_event_titles": [
    [
      "NBA Las Vegas Summer League 2026",
      361
    ],
    [
      "LiveNOW by FOX",
      245
    ],
    [
      "FOX News Talk",
      204
    ],
    [
      "American League - National League",
      162
    ],
    [
      "EWC - League of Legends - Day 1 - Stream B",
      128
    ],
    [
      "EWC - League of Legends - Day 1",
      128
    ],
    [
      "ML:BB Women - Day 2: Stream A",
      128
    ],
    [
      "Courtside - Live-Umag-ATP, Gstaad-ATP, Bastad-ATP, Athens-WTA & Iasi-WTA Early Rounds",
      125
    ],
    [
      "AMC",
      123
    ],
    [
      "IFC",
      123
    ],
    [
      "The Walking Dead Channel",
      123
    ],
    [
      "Sundance TV",
      123
    ],
    [
      "BBC America",
      123
    ],
    [
      "AMC +",
      123
    ],
    [
      "Cinemax Action",
      123
    ],
    [
      "Cinemax HD East",
      123
    ],
    [
      "Cinemax Classics",
      123
    ],
    [
      "Cinemax West",
      123
    ],
    [
      "Cinemax Hits",
      123
    ],
    [
      "MAX Latino East",
      123
    ],
    [
      "CNN Originals",
      123
    ],
    [
      "CNN Stream",
      123
    ],
    [
      "CNN International",
      123
    ],
    [
      "MGM+ MARQUEE",
      123
    ],
    [
      "MGM+ DRIVE-IN",
      123
    ],
    [
      "MGM+",
      123
    ],
    [
      "MGM+ HITS",
      123
    ],
    [
      "Fox Justice",
      123
    ],
    [
      "Fox Weather",
      123
    ],
    [
      "International Brawling Championship 4",
      123
    ],
    [
      "FOX 5 Washington, DC",
      122
    ],
    [
      "Fox 5 Plus",
      122
    ],
    [
      "FOX News Channel",
      122
    ],
    [
      "FS1",
      122
    ],
    [
      "FS2",
      122
    ],
    [
      "FOX Business",
      122
    ],
    [
      "FOX Weather",
      122
    ],
    [
      "Big Ten Network",
      122
    ],
    [
      "FOX Deportes",
      122
    ],
    [
      "FOX Soul",
      122
    ],
    [
      "The TMZ Channel",
      122
    ],
    [
      "The Masked Singer",
      122
    ],
    [
      "FOX Local Los Angeles",
      122
    ],
    [
      "FOX Local Detroit",
      122
    ],
    [
      "FOX Local Dallas Fort Worth",
      122
    ],
    [
      "FOX Local Atlanta",
      122
    ],
    [
      "FOX Local San Francisco",
      122
    ],
    [
      "FOX Local Orlando",
      122
    ],
    [
      "Lima - Day 1",
      119
    ],
    [
      "Chattanooga Chill at Atlanta Smoke",
      119
    ],
    [
      "Season 2026",
      116
    ],
    [
      "Collignon vs. Sonego",
      116
    ],
    [
      "EWC - Free Fire - Day 1",
      114
    ],
    [
      "Short Track Super Series at Bridgeport Motorsports Park",
      113
    ],
    [
      "Jul 14 - PTT Newport Beach",
      113
    ],
    [
      "Metropolitan Mojo at Atlantic Aces",
      113
    ],
    [
      "Tennis Today Live-Bastad-ATP, Gstaad-ATP & Iasi-WTA Rounds Rounds",
      113
    ],
    [
      "Van de Zandschulp vs. Vallejo",
      113
    ],
    [
      "Jul 15 - PTT Skopje",
      107
    ],
    [
      "Bulls vs. Wizards",
      106
    ],
    [
      "EWC - ML:BB Women - Day 2 - Stream B",
      99
    ],
    [
      "Wings vs. Liberty",
      90
    ],
    [
      "VPM (PBS WCVE)",
      82
    ],
    [
      "WETA (PBS WETA)",
      82
    ],
    [
      "Law & Order",
      82
    ],
    [
      "Dateline 24/7",
      82
    ],
    [
      "BET x Tyler Perry Comedy",
      82
    ],
    [
      "The First 48 by A&E",
      82
    ],
    [
      "Judy Justice",
      82
    ],
    [
      "Murder, She Wrote",
      82
    ],
    [
      "IShowSpeed",
      82
    ],
    [
      "ION",
      82
    ],
    [
      "The Incredible Dr. Pol",
      82
    ],
    [
      "Unspeakable",
      82
    ],
    [
      "20/20",
      82
    ],
    [
      "CNN Headlines",
      82
    ],
    [
      "Ancient Aliens",
      82
    ],
    [
      "Paternity Court",
      82
    ],
    [
      "My Wife and Kids",
      82
    ],
    [
      "ABC News Live",
      82
    ],
    [
      "In The Heat Of The Night",
      82
    ],
    [
      "CBS Sports HQ",
      62
    ],
    [
      "Jesser",
      62
    ],
    [
      "Celine Dept",
      62
    ],
    [
      "Jesse James West",
      62
    ],
    [
      "Futcrunch",
      62
    ],
    [
      "Tennis Channel 2",
      62
    ],
    [
      "FloRacing 24/7",
      62
    ],
    [
      "Willow Sports",
      62
    ],
    [
      "Ryz Sports",
      62
    ],
    [
      "RugbyPass TV",
      62
    ],
    [
      "Pickleballtv",
      62
    ],
    [
      "CBS Sports Golazo Network",
      62
    ],
    [
      "Scripps Sports",
      62
    ],
    [
      "World Poker Tour",
      62
    ],
    [
      "HBO Boxing",
      62
    ],
    [
      "Billiard TV",
      62
    ],
    [
      "Monster Jam",
      62
    ],
    [
      "Stadium",
      62
    ],
    [
      "SPEED SPORT 1",
      62
    ]
  ],
  "files": {
    "summary": "public/probes/prime_livetv_primehd_summary.json",
    "pages": "public/probes/prime_livetv_primehd_pages.json",
    "links": "public/probes/prime_livetv_primehd_links.json",
    "fetched_links": "public/probes/prime_livetv_primehd_fetched_links.json",
    "stations": "public/probes/prime_livetv_primehd_stations.json",
    "schedule_events": "public/probes/prime_livetv_primehd_schedule_events.json",
    "prime_candidates": "public/probes/prime_livetv_primehd_prime_candidates.json",
    "prime_sport_candidates": "public/probes/prime_livetv_primehd_prime_sport_candidates.json",
    "hints": "public/probes/prime_livetv_primehd_hints.json"
  }
}