{
  "ok": true,
  "generated_at_utc": "2026-07-07T17:55:08.631653+00:00",
  "seed_urls": [
    "https://www.primevideo.com/-/de/sports?ref_=atv_hm_sports_c_9zZ8D2_hom",
    "https://www.primevideo.com/-/en/sports?ref_=atv_hm_sports_c_9zZ8D2_hom",
    "https://www.amazon.de/-/de/gp/video/sports",
    "https://www.amazon.de/-/en/gp/video/sports"
  ],
  "known_extra_urls": [
    "https://www.primevideo.com/-/de/tournament/amzn1.dv.icid.70b8ac67-d420-4c70-a0b7-3e53868a4968?tr=at",
    "https://www.amazon.de/-/de/gp/video/tournament/amzn1.dv.icid.70b8ac67-d420-4c70-a0b7-3e53868a4968"
  ],
  "pages_total": 6,
  "pages_ok": 6,
  "discovered_links_total": 1520,
  "fetched_discovered_total": 100,
  "fetched_discovered_ok": 19,
  "containers_total": 163,
  "events_total": 1936,
  "events_unique": 803,
  "keyword_events": 803,
  "live_tv_like_events": 274,
  "slot_hints": 7711,
  "top_containers": [
    [
      "Carousel Title",
      15
    ],
    [
      "Kürzlich beendet",
      10
    ],
    [
      "Bevorstehende Live-Veranstaltungen",
      8
    ],
    [
      "Rund um die Uhr live: Serien, Dokumentationen und mehr.",
      8
    ],
    [
      "All or Nothing",
      6
    ],
    [
      "Universal Tennis",
      6
    ],
    [
      "Live and upcoming",
      6
    ],
    [
      "Sport-Zusatzkanäle",
      5
    ],
    [
      "ZDF: FIFA Fussball-Weltmeisterschaft 2026™ live- und bevorstehend",
      4
    ],
    [
      "Formel 1",
      4
    ],
    [
      "Sieh dir Top-Kampfsport an",
      4
    ],
    [
      "Für die Fußballfans unter uns",
      4
    ],
    [
      "Sportdokumentationen",
      4
    ],
    [
      "Auf Sieg spielen",
      4
    ],
    [
      "Mit einer Zusatzkanal-Buchung ansehen",
      4
    ],
    [
      "Unavailable due to location restrictions",
      4
    ],
    [
      "Nicht verfügbar auf MLB Network",
      4
    ],
    [
      "Boxing Highlights",
      4
    ],
    [
      "Fußball-Highlights",
      4
    ],
    [
      "General Sports Highlights",
      4
    ],
    [
      "Entdecke weitere Ligen",
      3
    ],
    [
      "Sports subscriptions",
      2
    ],
    [
      "Mit einer Zusatzkanal-Buchung ansehen – Vollständige Wiederholungen",
      2
    ],
    [
      "Mehr Ereignisse",
      2
    ],
    [
      "Sport Documentaries",
      2
    ],
    [
      "Playing to Win",
      2
    ],
    [
      "Rund um die Uhr live ansehen",
      2
    ],
    [
      "WTA – live und bevorstehend",
      2
    ],
    [
      "ATP – live und bevorstehend",
      2
    ],
    [
      "Serien und Originals",
      2
    ],
    [
      "WTA-Wiederholungen",
      2
    ],
    [
      "FIFA World Cup 2026™: Live- und bevorstehende Events",
      1
    ],
    [
      "Sport mit Zusatzkanal-Buchungen",
      1
    ],
    [
      "Sportsender – Live-Übertragung",
      1
    ],
    [
      "Sportdokumentationen und -serien",
      1
    ],
    [
      "FIFA World Cup 2026™ live and upcoming events",
      1
    ],
    [
      "Sports with a subscription",
      1
    ],
    [
      "Explore more leagues",
      1
    ],
    [
      "Sports stations – On now",
      1
    ],
    [
      "Sports documentaries and series",
      1
    ],
    [
      "ZDF: FIFA World Cup 2026™ live and upcoming",
      1
    ],
    [
      "Formula 1",
      1
    ],
    [
      "Watch top combat sports",
      1
    ],
    [
      "For the football fans amongst us",
      1
    ],
    [
      "Watch with a subscription – Live and upcoming",
      1
    ]
  ],
  "top_event_titles": [
    [
      "Courtside - Live-Newport-ATP/WTA Challenger Early Rounds",
      16
    ],
    [
      "Courtside - Live-Umag-ATP, Gstaad-ATP, Bastad-ATP, Athens-WTA & Iasi-WTA Early Rounds",
      12
    ],
    [
      "TBD vs. TBD",
      11
    ],
    [
      "F1 Weekend Warm-Up",
      10
    ],
    [
      "TNA iMPACT!",
      10
    ],
    [
      "EWC - Dota 2 - Week 1, Day 1 - Stream B",
      9
    ],
    [
      "EWC - Dota 2 - Week 1, Day 1 - Stream C",
      9
    ],
    [
      "EWC - Dota 2 - Week 1, Day 1 - Stream A",
      9
    ],
    [
      "EWC - Apex Legends - Day 1",
      9
    ],
    [
      "EWC - Valorant - Day 6",
      9
    ],
    [
      "Sri Lanka tour of West Indies 2026 - 2nd Test - West Indies vs Sri Lanka",
      9
    ],
    [
      "India tour of England 2026 - 3rd T20I - England vs India",
      9
    ],
    [
      "Lincer vs. Maria",
      9
    ],
    [
      "Volynets vs. Arseneault",
      9
    ],
    [
      "Season 2026",
      8
    ],
    [
      "The Unbeaten World Cup Show-Onwards and Upwards",
      7
    ],
    [
      "2026 USA National Pool Championships",
      7
    ],
    [
      "Spain vs. Fiji",
      7
    ],
    [
      "Georgia vs. Uruguay",
      7
    ],
    [
      "Georgia U20 v Uruguay U20",
      7
    ],
    [
      "Campeonato de Europa Femenino Sub-19 de la UEFA 2026",
      7
    ],
    [
      "Yankees - Rays",
      7
    ],
    [
      "RWS: Tapaokaew vs. McGreevy",
      7
    ],
    [
      "Courtside - Live-Umag-ATP Quarterfinals; Gstaad-ATP, Bastad-ATP, Athens-WTA & Iasi-WTA Early Rounds",
      6
    ],
    [
      "Courtside - Live-Umag-ATP Semifinals; Gstaad-ATP, Bastad-ATP, Athens-WTA & Iasi-WTA Quarterfinals",
      6
    ],
    [
      "Courtside - Live-Umag-ATP Singles Final; Gstaad-ATP, Bastad-ATP, Athens-WTA & Iasi-WTA Semifinals",
      6
    ],
    [
      "Argentinien vs. Ägypten",
      5
    ],
    [
      "Schweiz vs. Kolumbien",
      5
    ],
    [
      "Frankreich vs. Marokko",
      5
    ],
    [
      "Spanien vs. Belgien",
      5
    ],
    [
      "Norwegen vs. England",
      5
    ],
    [
      "Todo el Mundial (Julio 7)",
      5
    ],
    [
      "El Pelotazo (Julio 8)",
      5
    ],
    [
      "El Pelotazo (Julio 9)",
      5
    ],
    [
      "Hoy en el Mundial (Julio 9)",
      5
    ],
    [
      "Vive el Mundial (Julio 9)",
      5
    ],
    [
      "Todo el Mundial (Julio 9)",
      5
    ],
    [
      "El Pelotazo (Julio 10)",
      5
    ],
    [
      "Hoy en el Mundial (Julio 10)",
      5
    ],
    [
      "Vive el Mundial (Julio 10)",
      5
    ],
    [
      "Todo el Mundial (Julio 10)",
      5
    ],
    [
      "El Pelotazo (Julio 11)",
      5
    ],
    [
      "Hoy en el Mundial (Julio 11)",
      5
    ],
    [
      "Vive el Mundial (Julio 11)",
      5
    ],
    [
      "Inside The Ring - July 6",
      5
    ],
    [
      "OnlyWrestlers: Independence Rumble",
      5
    ],
    [
      "UFC Hall of Fame Induction Ceremony",
      5
    ],
    [
      "UFC 329: Press Conference",
      5
    ],
    [
      "UFC 329: Press Conference em Português",
      5
    ],
    [
      "UFC 329: Weigh-In Desk Show",
      5
    ],
    [
      "Real American Freestyle-RAF 05 Press Conference",
      5
    ],
    [
      "UFC 329: Ceremonial Weigh-In",
      5
    ],
    [
      "UFC 329: Ceremonial Weigh-In em Português",
      5
    ],
    [
      "UFC 329: English",
      5
    ],
    [
      "UFC 329 en Español",
      5
    ],
    [
      "UFC 329 em Português",
      5
    ],
    [
      "UFC 329: Multiview",
      5
    ],
    [
      "Redstall vs. Courtney",
      5
    ],
    [
      "The Dan Le Batard Show: 7.7.26",
      5
    ],
    [
      "Großbritannien: Sprint",
      4
    ],
    [
      "Großbritannien: Qualifying (Sky Sport)",
      4
    ],
    [
      "Großbritannien: Qualifying",
      4
    ],
    [
      "Großbritannien: Rennen (Sky Sport)",
      4
    ],
    [
      "Großbritannien: Rennen",
      4
    ],
    [
      "Großbritannien: Rennen (Kinder)",
      4
    ],
    [
      "Belgien: 1. Freies Training (Sky Sport)",
      4
    ],
    [
      "Belgien: 1. Freies Training",
      4
    ],
    [
      "Belgien: 2. Freies Training (Sky Sport)",
      4
    ],
    [
      "Belgien: 2. Freies Training",
      4
    ],
    [
      "Belgien: 3. Freies Training",
      4
    ],
    [
      "Belgien: 3. Freies Training (Sky Sport)",
      4
    ],
    [
      "Belgien: Qualifying (Sky Sport)",
      4
    ],
    [
      "Belgien: Qualifying",
      4
    ],
    [
      "Belgien: Rennen (Sky Sport)",
      4
    ],
    [
      "Belgien: Rennen",
      4
    ],
    [
      "Ungarn: 1. Freies Training (Sky Sport)",
      4
    ],
    [
      "Ungarn: 1. Freies Training",
      4
    ],
    [
      "All Elite Wrestling: Dynamite-Folge 27",
      4
    ],
    [
      "AEW Collision",
      4
    ],
    [
      "All Elite Wrestling: Dynamite-Folge 28",
      4
    ]
  ],
  "files": {
    "summary": "public/probes/prime_sports_discovery_summary.json",
    "seed_pages": "public/probes/prime_sports_discovery_seed_pages.json",
    "discovered_links": "public/probes/prime_sports_discovery_links.json",
    "fetched_discovered": "public/probes/prime_sports_discovery_fetched.json",
    "containers": "public/probes/prime_sports_discovery_containers.json",
    "events": "public/probes/prime_sports_discovery_events.json",
    "keyword_events": "public/probes/prime_sports_discovery_keyword_events.json",
    "live_tv_like_events": "public/probes/prime_sports_discovery_live_tv_like_events.json",
    "slot_hints": "public/probes/prime_sports_discovery_slot_hints.json"
  }
}