{
  "ok": true,
  "generated_at_utc": "2026-07-17T14:30:08.661387+00:00",
  "urls": [
    "https://www.primevideo.com/-/de/livetv",
    "https://www.primevideo.com/-/en/livetv",
    "https://www.primevideo.com/-/de/sports?ref_=atv_hm_sports_c_9zZ8D2_hom",
    "https://www.primevideo.com/-/en/sports?ref_=atv_hm_sports_c_9zZ8D2_hom",
    "https://www.amazon.de/-/de/gp/video/livetv",
    "https://www.amazon.de/-/en/gp/video/livetv",
    "https://www.amazon.de/-/de/gp/video/sports",
    "https://www.amazon.de/-/en/gp/video/sports"
  ],
  "pages_total": 8,
  "pages_ok": 8,
  "discovered_links": 1030,
  "fetched_links": 100,
  "fetched_links_ok": 100,
  "stations": 87426,
  "schedule_events": 12420,
  "prime_candidates": 95033,
  "prime_sport_candidates": 37504,
  "hints": 126106,
  "top_station_titles": [
    [
      "Live ansehen",
      2762
    ],
    [
      "Season 8",
      1287
    ],
    [
      "TMZ",
      984
    ],
    [
      "Season 2026",
      906
    ],
    [
      "LiveNOW from FOX",
      738
    ],
    [
      "TMZ Live",
      738
    ],
    [
      "ABC News Live",
      615
    ],
    [
      "FOX 2 San Francisco",
      574
    ],
    [
      "CNN Headline Express",
      492
    ],
    [
      "B1G Today",
      492
    ],
    [
      "FOX 2 Detroit Live",
      492
    ],
    [
      "LiveNOW by FOX",
      451
    ],
    [
      "Joker: Folie à Deux",
      451
    ],
    [
      "Season 11",
      390
    ],
    [
      "FOX News Talk",
      369
    ],
    [
      "Season 11 Premiere: Rita We Love Your Ora",
      369
    ],
    [
      "FOX 5 Atlanta News LIVE",
      369
    ],
    [
      "FOX 35 News +",
      369
    ],
    [
      "ABC News Live First",
      328
    ],
    [
      "My Soul to Take",
      328
    ],
    [
      "Joker",
      328
    ],
    [
      "LiveNOW From FOX",
      328
    ],
    [
      "Season 10",
      312
    ],
    [
      "Birds of Prey: The Emancipation of Harley Quinn",
      312
    ],
    [
      "48 Nations",
      248
    ],
    [
      "Stoker",
      246
    ],
    [
      "CNN News Central",
      246
    ],
    [
      "One World With Zain Asher and Bianna Golodryga",
      246
    ],
    [
      "Like it Or Not",
      246
    ],
    [
      "This Word Had Soul ... and Serious Pressure",
      246
    ],
    [
      "LiveNow",
      246
    ],
    [
      "America Reports",
      246
    ],
    [
      "Varney & Company",
      246
    ],
    [
      "The Big Money Show",
      246
    ],
    [
      "Total Sports 360",
      246
    ],
    [
      "Group B Premiere: The Wizard of Oz Night",
      246
    ],
    [
      "Group C Premiere: Billy Joel Night",
      246
    ],
    [
      "TV Theme Night",
      246
    ],
    [
      "AMC",
      205
    ],
    [
      "IFC",
      205
    ],
    [
      "The Walking Dead Channel",
      205
    ],
    [
      "Sundance TV",
      205
    ],
    [
      "BBC America",
      205
    ],
    [
      "AMC +",
      205
    ],
    [
      "Cinemax Action",
      205
    ],
    [
      "Cinemax HD East",
      205
    ],
    [
      "The Greatest Showman",
      205
    ],
    [
      "Cinemax Classics",
      205
    ],
    [
      "Cinemax West",
      205
    ],
    [
      "Cinemax Hits",
      205
    ],
    [
      "MAX Latino East",
      205
    ],
    [
      "CNN Originals",
      205
    ],
    [
      "CNN Stream",
      205
    ],
    [
      "What We Know With Max Foster",
      205
    ],
    [
      "CNN International",
      205
    ],
    [
      "MGM+ MARQUEE",
      205
    ],
    [
      "MGM+ DRIVE-IN",
      205
    ],
    [
      "MGM+",
      205
    ],
    [
      "MGM+ HITS",
      205
    ],
    [
      "Fox Justice",
      205
    ],
    [
      "Fox Weather",
      205
    ],
    [
      "Weather Command",
      205
    ],
    [
      "America's Weather Center",
      205
    ],
    [
      "FOX Weather Now",
      205
    ],
    [
      "FOX Weather Live",
      205
    ],
    [
      "The Brian Kilmeade Show",
      205
    ],
    [
      "FOX Across America With Jimmy Failla",
      205
    ],
    [
      "The Guy Benson Show",
      205
    ],
    [
      "FOX News Radio",
      205
    ],
    [
      "KTVU Plus",
      205
    ],
    [
      "FOX News Channel",
      205
    ],
    [
      "FS1",
      205
    ],
    [
      "FS2",
      205
    ],
    [
      "FOX Business",
      205
    ],
    [
      "FOX Weather",
      205
    ],
    [
      "Big Ten Network",
      205
    ],
    [
      "FOX Deportes",
      205
    ],
    [
      "FOX Soul",
      205
    ],
    [
      "The TMZ Channel",
      205
    ],
    [
      "The Masked Singer",
      205
    ],
    [
      "FOX Local Los Angeles",
      205
    ],
    [
      "FOX Local Detroit",
      205
    ],
    [
      "FOX Local Dallas Fort Worth",
      205
    ],
    [
      "FOX Local Atlanta",
      205
    ],
    [
      "FOX Local San Francisco",
      205
    ],
    [
      "FOX Local Orlando",
      205
    ],
    [
      "Prime-Mitglied werden",
      203
    ],
    [
      "2024: Colorado at Colorado State",
      186
    ],
    [
      "In Case You Missed It",
      164
    ],
    [
      "Mom's Away",
      164
    ],
    [
      "ABC News Live Reports",
      164
    ],
    [
      "Todesfahrt",
      156
    ],
    [
      "Mordreihe",
      156
    ],
    [
      "Spieglein, Spieglein an der Wand",
      156
    ],
    [
      "Das Spiel mit der Zeit",
      156
    ],
    [
      "Ägyptische Götter",
      156
    ],
    [
      "Außergewöhnliche Begegnungen",
      156
    ],
    [
      "Sport",
      156
    ],
    [
      "Unspeakable",
      127
    ],
    [
      "Training W/ NFL’s Strongest Tight End “GRONK”",
      124
    ]
  ],
  "top_event_titles": [
    [
      "LiveNOW by FOX",
      246
    ],
    [
      "FOX News Talk",
      205
    ],
    [
      "NBA Las Vegas Summer League 2026",
      198
    ],
    [
      "Tour de France: Stage 13",
      177
    ],
    [
      "AMC",
      123
    ],
    [
      "IFC",
      123
    ],
    [
      "The Walking Dead Channel",
      123
    ],
    [
      "Sundance TV",
      123
    ],
    [
      "BBC America",
      123
    ],
    [
      "AMC +",
      123
    ],
    [
      "Cinemax Action",
      123
    ],
    [
      "Cinemax HD East",
      123
    ],
    [
      "Cinemax Classics",
      123
    ],
    [
      "Cinemax West",
      123
    ],
    [
      "Cinemax Hits",
      123
    ],
    [
      "MAX Latino East",
      123
    ],
    [
      "CNN Originals",
      123
    ],
    [
      "CNN Stream",
      123
    ],
    [
      "CNN International",
      123
    ],
    [
      "MGM+ MARQUEE",
      123
    ],
    [
      "MGM+ DRIVE-IN",
      123
    ],
    [
      "MGM+",
      123
    ],
    [
      "MGM+ HITS",
      123
    ],
    [
      "Fox Justice",
      123
    ],
    [
      "Fox Weather",
      123
    ],
    [
      "FOX 2 San Francisco",
      123
    ],
    [
      "KTVU Plus",
      123
    ],
    [
      "FOX News Channel",
      123
    ],
    [
      "FS1",
      123
    ],
    [
      "FS2",
      123
    ],
    [
      "FOX Business",
      123
    ],
    [
      "FOX Weather",
      123
    ],
    [
      "Big Ten Network",
      123
    ],
    [
      "FOX Deportes",
      123
    ],
    [
      "FOX Soul",
      123
    ],
    [
      "The TMZ Channel",
      123
    ],
    [
      "The Masked Singer",
      123
    ],
    [
      "FOX Local Los Angeles",
      123
    ],
    [
      "FOX Local Detroit",
      123
    ],
    [
      "FOX Local Dallas Fort Worth",
      123
    ],
    [
      "FOX Local Atlanta",
      123
    ],
    [
      "FOX Local San Francisco",
      123
    ],
    [
      "FOX Local Orlando",
      123
    ],
    [
      "Tennis Today Live-Bastad-ATP, Gstaad-ATP & Iasi-WTA Quarterfinals",
      121
    ],
    [
      "EWC - ML:BB Women - Day 4",
      121
    ],
    [
      "EWC - Free Fire - Day 3",
      121
    ],
    [
      "EWC - Dota 2 - Week 2, Day 4",
      121
    ],
    [
      "EWC - League of Legends - Day 3",
      121
    ],
    [
      "EWC - League of Legends - Day 3 - Stream B",
      121
    ],
    [
      "Monaco - Qualifying Sessions and Pole Shootout",
      121
    ],
    [
      "T20 Blast 2026 - Semi-Final 2 - Hampshire Women vs Durham Women",
      118
    ],
    [
      "Lanka Premier League 2026 - 1st Match - Jaffna Kings vs Galle Gallants",
      118
    ],
    [
      "The Open: Rd. 2",
      115
    ],
    [
      "Jul 17 - PTT Skopje",
      115
    ],
    [
      "2026 Predator European Championships: Slovenia",
      115
    ],
    [
      "Courtside - Live-Umag-ATP Semifinals; Gstaad-ATP, Bastad-ATP, Athens-WTA & Iasi-WTA Quarterfinals",
      115
    ],
    [
      "Live At The Range",
      115
    ],
    [
      "The Open All-Access: Rd. 2",
      115
    ],
    [
      "Rublev vs. Baez",
      115
    ],
    [
      "A./Kempen vs. Kulambayeva/Charaeva",
      104
    ],
    [
      "ONE Friday Fights 162",
      103
    ],
    [
      "Oliynykova vs. Burel",
      102
    ],
    [
      "KC Current - San Diego Wave",
      90
    ],
    [
      "KQED (PBS KQED)",
      82
    ],
    [
      "Law & Order",
      82
    ],
    [
      "Dateline 24/7",
      82
    ],
    [
      "BET x Tyler Perry Comedy",
      82
    ],
    [
      "The First 48 by A&E",
      82
    ],
    [
      "Judy Justice",
      82
    ],
    [
      "Murder, She Wrote",
      82
    ],
    [
      "IShowSpeed",
      82
    ],
    [
      "ION",
      82
    ],
    [
      "The Incredible Dr. Pol",
      82
    ],
    [
      "Unspeakable",
      82
    ],
    [
      "20/20",
      82
    ],
    [
      "CNN Headlines",
      82
    ],
    [
      "Ancient Aliens",
      82
    ],
    [
      "Paternity Court",
      82
    ],
    [
      "My Wife and Kids",
      82
    ],
    [
      "ABC News Live",
      82
    ],
    [
      "In The Heat Of The Night",
      82
    ],
    [
      "NBC Comedy Vault",
      82
    ],
    [
      "CBS Sports HQ",
      62
    ],
    [
      "Jesser",
      62
    ],
    [
      "Celine Dept",
      62
    ],
    [
      "Jesse James West",
      62
    ],
    [
      "Futcrunch",
      62
    ],
    [
      "Tennis Channel 2",
      62
    ],
    [
      "FloRacing 24/7",
      62
    ],
    [
      "Willow Sports",
      62
    ],
    [
      "Ryz Sports",
      62
    ],
    [
      "RugbyPass TV",
      62
    ],
    [
      "Pickleballtv",
      62
    ],
    [
      "CBS Sports Golazo Network",
      62
    ],
    [
      "Scripps Sports",
      62
    ],
    [
      "World Poker Tour",
      62
    ],
    [
      "HBO Boxing",
      62
    ],
    [
      "Billiard TV",
      62
    ],
    [
      "Monster Jam",
      62
    ],
    [
      "Stadium",
      62
    ]
  ],
  "files": {
    "summary": "public/probes/prime_livetv_primehd_summary.json",
    "pages": "public/probes/prime_livetv_primehd_pages.json",
    "links": "public/probes/prime_livetv_primehd_links.json",
    "fetched_links": "public/probes/prime_livetv_primehd_fetched_links.json",
    "stations": "public/probes/prime_livetv_primehd_stations.json",
    "schedule_events": "public/probes/prime_livetv_primehd_schedule_events.json",
    "prime_candidates": "public/probes/prime_livetv_primehd_prime_candidates.json",
    "prime_sport_candidates": "public/probes/prime_livetv_primehd_prime_sport_candidates.json",
    "hints": "public/probes/prime_livetv_primehd_hints.json"
  }
}